{
  "$schema": "https://json-structure.org/meta/core/v0/#",
  "$id": "https://raw.githubusercontent.com/api-evangelist/webex/refs/heads/main/json-structure/broadworks-acd-object-device-structure.json",
  "name": "AcdObjectDevice",
  "description": "AcdObjectDevice schema from Webex API",
  "type": "object",
  "properties": {
    "enabled": {
      "type": "boolean",
      "example": true,
      "description": "Indicates whether the ACD object is enabled."
    },
    "displayCallqueueAgentSoftkeys": {
      "$ref": "#/components/schemas/DisplayCallqueueAgentSoftkeysObject",
      "description": "Indicates the call queue agent soft key value of an ACD object."
    }
  },
  "required": [
    "enabled",
    "displayCallqueueAgentSoftkeys"
  ]
}